<?xml version="1.0" encoding="utf-8"?>
<dialog firstMasterID="5">
  <message userID="5" sent_at="2018:05:17T00:04:00">
    <text>hello</text>
  </message>
  <message userID="5" sent_at="2018:05:17T00:04:28">
    <text>fine, thanks</text>
  </message>
  <message userID="5" sent_at="2018:05:17T00:09:07">
    <text>hi</text>
  </message>
  <message userID="5" sent_at="2018:05:17T00:09:14">
    <text>how are you</text>
  </message>
  <message userID="5" sent_at="2018:05:17T00:09:26">
    <text>i am fine thncs</text>
  </message>
  <message userID="5" sent_at="2018:05:17T00:16:59">
    <text>new file</text>
    <contentID>1036</contentID>
  </message>
  <message userID="5" sent_at="2018:05:17T00:42:35">
    <text>new button</text>
  </message>
  <message userID="5" sent_at="2018:05:17T00:51:07">
    <text>There are a lot of text to test multiline text and i hope it will work because it's late rigth now and i dont want fix it and just go to hit the sack</text>
  </message>
  <message userID="5" sent_at="2018:05:21T00:14:35">
    <text></text>
  </message>
  <message userID="5" sent_at="2018:05:21T00:58:26">
    <text></text>
    <contentID>1095</contentID>
  </message>
  <message userID="5" sent_at="2018:05:21T09:13:00">
    <text>rerewr</text>
  </message>
  <message userID="5" sent_at="2018:05:21T20:02:01">
    <text>hello</text>
    <contentID>1114</contentID>
  </message>
</dialog>